.gitignore
Dockerfile
overview.ipynb
overview.slides.html
setup.py
euler202/__init__.py
euler202/__main__.py
euler202/soln.py
euler202.egg-info/PKG-INFO
euler202.egg-info/SOURCES.txt
euler202.egg-info/dependency_links.txt
euler202.egg-info/requires.txt
euler202.egg-info/top_level.txt