Metadata-Version: 1.0
Name: euler202
Version: 0.0.3
Summary: Solves Euler problem 202
Home-page: https://github.com/MarkCBell/euler202
Author: Mark Bell
Author-email: mcbell@illinois.edu
License: MIT License
Platform: UNKNOWN
